trellis/__init__.py
trellis/datasets/__init__.py
trellis/datasets/components.py
trellis/datasets/sparse_feat2render.py
trellis/datasets/sparse_structure.py
trellis/datasets/sparse_structure_latent.py
trellis/datasets/structured_latent.py
trellis/datasets/structured_latent2render.py
trellis/dinov2/__init__.py
trellis/dinov2/hub/__init__.py
trellis/dinov2/hub/backbones.py
trellis/dinov2/hub/utils.py
trellis/dinov2/layers/__init__.py
trellis/dinov2/layers/attention.py
trellis/dinov2/layers/block.py
trellis/dinov2/layers/dino_head.py
trellis/dinov2/layers/drop_path.py
trellis/dinov2/layers/layer_scale.py
trellis/dinov2/layers/mlp.py
trellis/dinov2/layers/patch_embed.py
trellis/dinov2/layers/swiglu_ffn.py
trellis/dinov2/models/__init__.py
trellis/dinov2/models/vision_transformer.py
trellis/dinov2/utils/__init__.py
trellis/dinov2/utils/cluster.py
trellis/dinov2/utils/config.py
trellis/dinov2/utils/dtype.py
trellis/dinov2/utils/param_groups.py
trellis/dinov2/utils/utils.py
trellis/models/__init__.py
trellis/models/sparse_elastic_mixin.py
trellis/models/sparse_structure_flow.py
trellis/models/sparse_structure_vae.py
trellis/models/structured_latent_flow.py
trellis/models/structured_latent_vae/__init__.py
trellis/models/structured_latent_vae/base.py
trellis/models/structured_latent_vae/decoder_gs.py
trellis/models/structured_latent_vae/decoder_mesh.py
trellis/models/structured_latent_vae/decoder_rf.py
trellis/models/structured_latent_vae/encoder.py
trellis/modules/__init__.py
trellis/modules/norm.py
trellis/modules/spatial.py
trellis/modules/utils.py
trellis/modules/attention/__init__.py
trellis/modules/attention/full_attn.py
trellis/modules/attention/modules.py
trellis/modules/sparse/__init__.py
trellis/modules/sparse/basic.py
trellis/modules/sparse/linear.py
trellis/modules/sparse/nonlinearity.py
trellis/modules/sparse/norm.py
trellis/modules/sparse/spatial.py
trellis/modules/sparse/attention/__init__.py
trellis/modules/sparse/attention/full_attn.py
trellis_3d_python-0.1.23.dist-info/licenses/LICENSE
trellis_3d_python-0.1.23.dist-info/METADATA
trellis_3d_python-0.1.23.dist-info/WHEEL
trellis_3d_python-0.1.23.dist-info/top_level.txt
trellis_3d_python-0.1.23.dist-info/RECORD
