Metadata-Version: 2.4
Name: trellis-3d-python
Version: 0.1.23
Summary: TRELLIS is a large 3D asset generation model.
Home-page: https://github.com/microsoft/trellis
Author: Microsoft Corporation
Author-email: t-jxiang@microsoft.com
License: MIT
Classifier: Programming Language :: Python :: 3
Classifier: License :: OSI Approved :: MIT License
Classifier: Operating System :: OS Independent
Requires-Python: >=3.8
License-File: LICENSE
Requires-Dist: torch
Requires-Dist: numpy
Dynamic: author
Dynamic: author-email
Dynamic: classifier
Dynamic: description
Dynamic: description-content-type
Dynamic: home-page
Dynamic: license
Dynamic: license-file
Dynamic: requires-dist
Dynamic: requires-python
Dynamic: summary
